nchainz/__init__.py
nchainz/tests/__init__.py
nchainz/tests/test_example.py
nchainz-1.0.0.dist-info/LICENSE
nchainz-1.0.0.dist-info/WHEEL
nchainz-1.0.0.dist-info/METADATA
nchainz-1.0.0.dist-info/RECORD
