Metadata-Version: 2.1
Name: nchainz
Version: 1.0.0
Summary: Like 2 Chainz but better!
Home-page: https://github.com/lquenti/nchainz
License: MIT
Author: Lars Quentin
Author-email: lars@lquenti.de
Requires-Python: >=3.7,<4.0
Classifier: License :: OSI Approved :: MIT License
Classifier: Programming Language :: Python :: 3
Classifier: Programming Language :: Python :: 3.10
Classifier: Programming Language :: Python :: 3.7
Classifier: Programming Language :: Python :: 3.8
Classifier: Programming Language :: Python :: 3.9
Project-URL: Repository, https://github.com/lquenti/nchainz
